cpu/Instruction_Memory/Instruction_Memory.v
/*
Module	: 1024x8-bit instruction memory (4-Byte blocks)



This memory allows instructions to be read as 4-Byte blocks
*/
`timescale 1ns/100ps
module instruction_memory(
	CLK,
    PC,
    INSTRUCTION,
);
input				CLK;
input[31:0]			PC;
output reg [31:0]	INSTRUCTION;


//Declare memory array 1024x8-bits 
reg [7:0] memory_array [1023:0];

//Initialize instruction memory
initial
begin
	
	
    // Sample program given below. You may hardcode your software program here, or load it from a file:
    {memory_array[10'd3],  memory_array[10'd2],  memory_array[10'd1],  memory_array[10'd0]}  = 32'b00000001000000010000000000010011; // addi x1, x0, 10
	{memory_array[10'd7],  memory_array[10'd6],  memory_array[10'd5],  memory_array[10'd4]}  = 32'b00000010000000100000000000010011; // addi x2, x0, 20
    {memory_array[10'd11], memory_array[10'd10], memory_array[10'd9],  memory_array[10'd8]}  = 32'b00000011000100010000000000110011; // add  x3, x1, x2
    {memory_array[10'd15], memory_array[10'd14], memory_array[10'd13], memory_array[10'd12]} = 32'b00000000000000110000000000100011; // sw   x3, 0(x0)

    // this code effectively adds the values 10 and 20 together, and stores the result (30) in memory address 0.
   

	// loading instr_mem content from instr_mem.mem file
	// $readmemb("instr_mem.mem", memory_array);
end


//Reading
// 3 TIME UNITS OF READING DEALY
always @( posedge CLK )
begin
#2
		INSTRUCTION[7:0]     =  memory_array[{PC+32'b00000000}];
		INSTRUCTION[15:8]    =  memory_array[{PC+32'b00000001}];
		INSTRUCTION[23:16]   =  memory_array[{PC+32'b00000010}];
		INSTRUCTION[31:24]   =  memory_array[{PC+32'b00000011}];
		
	
end


 
endmodule

cpu/Instruction_Memory/instruction_memory_tb.v
`include "Instruction_Memory.v"

`timescale 1ns/100ps
module instruction_memory_tb;
    reg CLK;
    reg [31:0] PC;
    wire [31:0] INSTRUCTION;

    instruction_memory DUT(
        .CLK(CLK),
        .PC(PC),
        .INSTRUCTION(INSTRUCTION)
    );

    initial begin
        CLK = 0;
        
        PC = 0;
        #10;
        $display("Instruction at address %0d: %b", PC, INSTRUCTION);
    
        
        PC = 4;
        #10;
        $display("Instruction at address %0d: %b", PC, INSTRUCTION);

        PC = 8;
        #10;
        $display("Instruction at address %0d: %b", PC, INSTRUCTION);

        PC = 12;
        #10;
        $display("Instruction at address %0d: %b", PC, INSTRUCTION);

        $finish;
    end

    always #5 CLK = ~CLK;

    initial begin
        $dumpfile("instruction_memory_tb.vcd");
        $dumpvars;
    end
endmodule

cpu/Instruction_Memory/instruction_memory_tb.vcd
$date
	Sun Apr  9 12:16:03 2023
$end
$version
	Icarus Verilog
$end
$timescale
	100ps
$end
$scope module instruction_memory_tb $end
$var wire 32 ! INSTRUCTION [31:0] $end
$var reg 1 " CLK $end
$var reg 32 # PC [31:0] $end
$scope module DUT $end
$var wire 1 " CLK $end
$var wire 32 $ PC [31:0] $end
$var reg 32 % INSTRUCTION [31:0] $end
$upscope $end
$upscope $end
$enddefinitions $end
#0
$dumpvars
bx %
b0 $
b0 #
0"
bx !
$end
#50
1"
#70
b1000000010000000000010011 !
b1000000010000000000010011 %
#100
0"
b100 #
b100 $
#150
1"
#170
b10000000100000000000010011 !
b10000000100000000000010011 %
#200
0"
b1000 #
b1000 $
#250
1"
#270
b11000100010000000000110011 !
b11000100010000000000110011 %
#300
0"
b1100 #
b1100 $
#350
1"
#370
b110000000000100011 !
b110000000000100011 %
