cpu/RegisterFile/reg_file.v
// Advanced Computer Architecture (CO502)
// Design: Register File
// Group Number: 4
// E Numbers: E/18/077, E/18/397, E/18/402
// Names: Nipun Dharmarathne, Shamod Wijerathne, Chatura Wimalasiri

module reg_file(IN, OUT1, OUT2, INADDRESS, OUT1ADDRESS, OUT2ADDRESS, WRITE, CLK, RESET);
    //Port declarations
    input [31:0] IN;                                    //Define 32bit input
    output [31:0] OUT1, OUT2;                           //Define 32bit outputs
    input [4:0] INADDRESS, OUT1ADDRESS, OUT2ADDRESS;    //Define 5 bit addresses
	input WRITE, CLK, RESET;                            //Define input signals

    reg [31:0] register [0:31];     //32 element array of 32 bit registers	             
    integer i;                      //Counter variable 
	
    //Register read
    //These assign statements are executed asynchrnously    
	assign #2 OUT1 = register[OUT1ADDRESS];
	assign #2 OUT2 = register[OUT2ADDRESS];

    //The always block triggeres (synchronously) only for the positive edge of the clock pulse
	always @(posedge CLK) begin
        if (RESET) begin
            //Resetting all register values to zero when RESET signal is high
            #1
            for (i=0; i<32; i=i+1) begin
                register[i] <= 0;
            end
        end

        else begin
            //Write data to the register when write signal is high
            if (WRITE) #1 register[INADDRESS] <= IN;
        end
	end     
endmodule

module reg_file_tb();
    reg [31:0] WRITEDATA;
    reg [4:0] WRITEREG, READREG1, READREG2;
    reg CLK, RESET, WRITEENABLE; 
    wire [31:0] REGOUT1, REGOUT2;    

    reg_file myregfile(WRITEDATA, REGOUT1, REGOUT2, WRITEREG, READREG1, READREG2, WRITEENABLE, CLK, RESET);

    initial
    begin
        CLK = 1'b1;
        
        // generate files needed to plot the waveform using GTKWave
        $dumpfile("reg_file_wavedata.vcd");
		$dumpvars(0, reg_file_tb);
        
        // assign values with time to input signals to see output 
        RESET = 1'b0;
        WRITEENABLE = 1'b0;
        
        #5
        RESET = 1'b1;
        READREG1 = 5'd0;
        READREG2 = 5'd4;
        
        #7
        RESET = 1'b0;
        
        #3
        WRITEREG = 5'd2;
        WRITEDATA = 32'd95;
        WRITEENABLE = 1'b1;
        
        #9
        WRITEENABLE = 1'b0;
        
        #1
        READREG1 = 5'd2;
        
        #9
        WRITEREG = 5'd1;
        WRITEDATA = 32'd28;
        WRITEENABLE = 1'b1;
        READREG1 = 5'd1;
        
        #10
        WRITEENABLE = 1'b0;
        
        #10
        WRITEREG = 5'd4;
        WRITEDATA = 32'd6;
        WRITEENABLE = 1'b1;
        
        #10
        WRITEDATA = 32'd15;
        WRITEENABLE = 1'b1;
        
        #10
        WRITEENABLE = 1'b0;
        
        #6
        WRITEREG = 5'd1;
        WRITEDATA = 32'd50;
        WRITEENABLE = 1'b1;
        
        #5
        WRITEENABLE = 1'b0;
        
        #10
        $finish;
    end
    
    // clock signal generation
    always
        #5 CLK = ~CLK;
       
endmodule

cpu/RegisterFile/reg_file_wavedata.vcd
$date
	Wed Apr 05 22:36:01 2023
$end
$version
	Icarus Verilog
$end
$timescale
	1s
$end
$scope module reg_file_tb $end
$var wire 32 ! REGOUT1 [31:0] $end
$var wire 32 " REGOUT2 [31:0] $end
$var reg 1 # CLK $end
$var reg 5 $ READREG1 [4:0] $end
$var reg 5 % READREG2 [4:0] $end
$var reg 1 & RESET $end
$var reg 32 ' WRITEDATA [31:0] $end
$var reg 1 ( WRITEENABLE $end
$var reg 5 ) WRITEREG [4:0] $end
$scope module myregfile $end
$var wire 1 * CLK $end
$var wire 32 + IN [31:0] $end
$var wire 5 , INADDRESS [4:0] $end
$var wire 32 - OUT1 [31:0] $end
$var wire 5 . OUT1ADDRESS [4:0] $end
$var wire 32 / OUT2 [31:0] $end
$var wire 5 0 OUT2ADDRESS [4:0] $end
$var wire 1 1 RESET $end
$var wire 1 2 WRITE $end
$var integer 32 3 i [31:0] $end
$upscope $end
$upscope $end
$enddefinitions $end
#0
$dumpvars
bx 3
02
01
bx 0
bx /
bx .
bx -
bx ,
bx +
1*
bx )
0(
bx '
0&
bx %
bx $
1#
bx "
bx !
$end
#5
0#
0*
b100 %
b100 0
b0 $
b0 .
1&
11
#10
1#
1*
#11
b100000 3
#12
0&
01
#13
b0 "
b0 /
b0 !
b0 -
#15
1(
12
b1011111 '
b1011111 +
b10 )
b10 ,
0#
0*
#20
1#
1*
#24
0(
02
#25
b10 $
b10 .
0#
0*
#27
b1011111 !
b1011111 -
#30
1#
1*
#34
b1 $
b1 .
1(
12
b11100 '
b11100 +
b1 )
b1 ,
#35
0#
0*
#36
b0 !
b0 -
#40
1#
1*
#43
b11100 !
b11100 -
#44
0(
02
#45
0#
0*
#50
1#
1*
#54
1(
12
b110 '
b110 +
b100 )
b100 ,
#55
0#
0*
#60
1#
1*
#63
b110 "
b110 /
#64
b1111 '
b1111 +
#65
0#
0*
#70
1#
1*
#73
b1111 "
b1111 /
#74
0(
02
#75
0#
0*
#80
1#
1*
1(
12
b110010 '
b110010 +
b1 )
b1 ,
#83
b110010 !
b110010 -
#85
0#
0*
0(
02
